Metadata-Version: 1.0
Name: malis
Version: 1.0
Summary: MALIS segmentation loss function
Home-page: https://github.com/TuragaLab/malis
Author: Srinivas Turaga
Author-email: turagas@janelia.hhmi.org
License: MIT
Platform: UNKNOWN
